{"revision":0,"last_node_id":5037,"last_link_id":0,"nodes":[{"id":5037,"type":"b6a5489a-8484-4702-b9d9-aba48382a085","pos":[11842.864285703332,-387.5279260254081],"size":[600,1225],"flags":{},"order":10,"mode":0,"inputs":[{"name":"IMAGE","type":"IMAGE","link":null},{"name":"LOG","type":"CMK_LOG_PIPE","link":null},{"name":"SAVE ENABLED","type":"BOOLEAN","widget":{"name":"SAVE ENABLED"},"link":null},{"name":"FILENAME PREFIX","type":"STRING","widget":{"name":"FILENAME PREFIX"},"link":null},{"name":"OUTPUT FOLDER","type":"STRING","widget":{"name":"OUTPUT FOLDER"},"link":null},{"label":"UPSCALE ENABLED","name":"enable","type":"BOOLEAN","widget":{"name":"enable"},"link":null}],"outputs":[],"properties":{"proxyWidgets":[["4919","SAVE ENABLED"],["4919","FILENAME PREFIX"],["4919","OUTPUT FOLDER"],["4913","enable"],["4751","compare_view"]],"cmkOuterSize":[600,1225]},"widgets_values":[],"color":"#232","bgcolor":"#353","shape":1,"title":"CMK Flow · 90 Upscale & Save"}],"links":[],"version":0.4,"definitions":{"subgraphs":[{"id":"b6a5489a-8484-4702-b9d9-aba48382a085","version":1,"state":{"lastGroupId":114,"lastNodeId":5037,"lastLinkId":12216,"lastRerouteId":0},"revision":0,"config":{},"name":"CMK Flow · 90 Upscale & Save","inputNode":{"id":-10,"bounding":[11609.399223976861,-572.0450216168146,161.51953125,168]},"outputNode":{"id":-20,"bounding":[13865,256,128,48]},"inputs":[{"id":"c57591ec-5b87-49d7-99d1-f02bf503f8f5","name":"IMAGE","type":"IMAGE","linkIds":[12009,12011],"pos":[11746.918755226861,-548.0450216168146]},{"id":"832b83b7-f693-42bf-b08e-cda5149f85e7","name":"LOG","type":"CMK_LOG_PIPE","linkIds":[12010],"pos":[11746.918755226861,-528.0450216168146]},{"id":"7f001d73-e491-434d-a4b0-5dee21953017","name":"SAVE ENABLED","type":"BOOLEAN","linkIds":[12036],"pos":[11746.918755226861,-508.04502161681455]},{"id":"b428c5f0-ffae-4b9b-a032-6b271d58643d","name":"FILENAME PREFIX","type":"STRING","linkIds":[12037],"pos":[11746.918755226861,-488.04502161681455]},{"id":"510c71b3-0124-4139-a92e-b8436125005f","name":"OUTPUT FOLDER","type":"STRING","linkIds":[12038],"pos":[11746.918755226861,-468.04502161681455]},{"id":"81b5c9e2-97f3-4b71-9df0-b21cd3b77b8f","name":"enable","type":"BOOLEAN","linkIds":[12202],"label":"UPSCALE ENABLED","pos":[11746.918755226861,-448.04502161681455]}],"outputs":[],"widgets":[],"nodes":[{"id":4751,"type":"ImageCompare","pos":[12090,-565],"size":[1180,1720],"flags":{"collapsed":false},"order":0,"mode":0,"inputs":[{"localized_name":"image_a","name":"image_a","shape":7,"type":"IMAGE","link":12012},{"localized_name":"image_b","name":"image_b","shape":7,"type":"IMAGE","link":12011},{"localized_name":"compare_view","name":"compare_view","type":"IMAGECOMPARE","widget":{"name":"compare_view"},"link":null}],"outputs":[],"properties":{"Node name for S&R":"ImageCompare","comparer_mode":"Click","default_output":"b"},"widgets_values":[],"color":"#222","bgcolor":"#000","shape":1},{"id":4913,"type":"CMK_SmartUpscalerPipe","pos":[11790,-560],"size":[285,305],"flags":{},"order":1,"mode":0,"inputs":[{"localized_name":"IMAGE","name":"IMAGE","type":"IMAGE","link":12009},{"localized_name":"LOG","name":"LOG","type":"CMK_LOG_PIPE","link":12010},{"localized_name":"enable","name":"enable","type":"BOOLEAN","widget":{"name":"enable"},"link":12202},{"localized_name":"limit_4x_mp","name":"limit_4x_mp","type":"FLOAT","widget":{"name":"limit_4x_mp"},"link":null},{"localized_name":"limit_2x_mp","name":"limit_2x_mp","type":"FLOAT","widget":{"name":"limit_2x_mp"},"link":null},{"localized_name":"model_4x","name":"model_4x","type":"COMBO","widget":{"name":"model_4x"},"link":null},{"localized_name":"model_2x","name":"model_2x","type":"COMBO","widget":{"name":"model_2x"},"link":null}],"outputs":[{"localized_name":"IMAGE","name":"IMAGE","type":"IMAGE","links":[12012,12034]},{"localized_name":"LOG","name":"LOG","type":"CMK_LOG_PIPE","links":[12035]},{"localized_name":"diagnostic","name":"diagnostic","type":"CMK_DIAGNOSTIC","links":null}],"properties":{"Node name for S&R":"CMK_SmartUpscalerPipe"},"widgets_values":[true,0.5,1.5,"RealESRGAN_x4plus.pth","RealESRGAN-x2plus.pth"],"shape":1},{"id":4919,"type":"CMK_SaveProjectImage","pos":[13295,-565],"size":[310,225],"flags":{},"order":2,"mode":0,"inputs":[{"localized_name":"IMAGE","name":"IMAGE","type":"IMAGE","link":12034},{"localized_name":"LOG","name":"LOG","type":"CMK_LOG_PIPE","link":12035},{"localized_name":"SAVE ENABLED","name":"SAVE ENABLED","type":"BOOLEAN","widget":{"name":"SAVE ENABLED"},"link":12036},{"localized_name":"FILENAME PREFIX","name":"FILENAME PREFIX","type":"STRING","widget":{"name":"FILENAME PREFIX"},"link":12037},{"localized_name":"OUTPUT FOLDER","name":"OUTPUT FOLDER","type":"STRING","widget":{"name":"OUTPUT FOLDER"},"link":12038},{"localized_name":"USE DATE FOLDER","name":"USE DATE FOLDER","type":"BOOLEAN","widget":{"name":"USE DATE FOLDER"},"link":null}],"outputs":[{"localized_name":"FULLPATH","name":"FULLPATH","type":"STRING","links":null}],"properties":{"Node name for S&R":"CMK_SaveProjectImage","cmkOuterSize":[310,225]},"widgets_values":[true,"image","",true],"shape":1}],"groups":[],"links":[{"id":12009,"origin_id":-10,"origin_slot":0,"target_id":4913,"target_slot":0,"type":"IMAGE"},{"id":12010,"origin_id":-10,"origin_slot":1,"target_id":4913,"target_slot":1,"type":"CMK_LOG_PIPE"},{"id":12011,"origin_id":-10,"origin_slot":0,"target_id":4751,"target_slot":1,"type":"IMAGE"},{"id":12012,"origin_id":4913,"origin_slot":0,"target_id":4751,"target_slot":0,"type":"IMAGE"},{"id":12034,"origin_id":4913,"origin_slot":0,"target_id":4919,"target_slot":0,"type":"IMAGE"},{"id":12035,"origin_id":4913,"origin_slot":1,"target_id":4919,"target_slot":1,"type":"CMK_LOG_PIPE"},{"id":12036,"origin_id":-10,"origin_slot":2,"target_id":4919,"target_slot":2,"type":"BOOLEAN"},{"id":12037,"origin_id":-10,"origin_slot":3,"target_id":4919,"target_slot":3,"type":"STRING"},{"id":12038,"origin_id":-10,"origin_slot":4,"target_id":4919,"target_slot":4,"type":"STRING"},{"id":12202,"origin_id":-10,"origin_slot":5,"target_id":4913,"target_slot":2,"type":"BOOLEAN"}],"extra":{}}]},"extra":{"CMKFlow":{"schemaVersion":2,"published":true,"category":"Finish","description":"Skaliert das fertige Bild hoch und bildet den speichernden Abschluss des CMK Flow.","status":"STABLE","order":90,"searchAliases":["upscale","save","finish","output"],"displayName":"90 Upscale & Save","domain":"Output","compatibility":["Image"],"version":"1.0.0","author":"CMK Nodes","features":["Ausgabebild hochskalieren","Dateiname und Zielordner steuern","Bild als Flow-Abschluss speichern"],"previews":[{"src":"assets/previews/upscale-save-outer.png","label":"Modul"},{"src":"assets/previews/upscale-save-inner.png","label":"Aufbau"}],"placementNote":"Als letzten Baustein des CMK Flow platzieren.","recommendedBefore":["30 Detailer","40 FaceSwap","50 FaceProcess"]}}}
